MANIFEST.in
README.md
setup.py
demo/hash_test.py
demo/redis_test.py
ring_redis/__init__.py
ring_redis/consistent_hash.py
ring_redis/redis_cache.py
ring_redis.egg-info/PKG-INFO
ring_redis.egg-info/SOURCES.txt
ring_redis.egg-info/dependency_links.txt
ring_redis.egg-info/not-zip-safe
ring_redis.egg-info/requires.txt
ring_redis.egg-info/top_level.txt
ring_redis/utils/__init__.py
ring_redis/utils/binary_search.py
ring_redis/utils/hash.py
ring_redis/utils/merge.py
ring_redis/utils/weighter.py