Metadata-Version: 1.1
Name: ring-redis
Version: 0.8.0
Summary: a lightweight, high available & extensible cache solution using redis
Home-page: https://github.com/luochen1990/ring_redis
Author: luo chen
Author-email: luochen1990@gmail.com
License: BSD
Keywords: redis,consistent hash,high available,HA,extensible,pure python
Platform: UNKNOWN
Classifier: Development Status :: 3 - Alpha
Classifier: Environment :: Web Environment
Classifier: Intended Audience :: Developers
Classifier: License :: OSI Approved :: BSD License
Classifier: Operating System :: OS Independent
Classifier: Programming Language :: Python
Classifier: Programming Language :: Python :: 3
Classifier: Topic :: Software Development :: Libraries :: Python Modules
